aio_omdb/__init__.py
aio_omdb/client.py
aio_omdb/exc.py
aio_omdb/model.py
aio_omdb/py.typed
aio_omdb-0.0.3.dist-info/LICENSE
aio_omdb-0.0.3.dist-info/METADATA
aio_omdb-0.0.3.dist-info/WHEEL
aio_omdb-0.0.3.dist-info/top_level.txt
aio_omdb-0.0.3.dist-info/RECORD
