Metadata-Version: 2.1
Name: aio-omdb
Version: 0.0.3
Summary: Asyncronous and synchronous Python client for OMDb (the Open Movie Database)
Home-page: https://github.com/altvod/aio-omdb
Author: Grigory Statsenko
Author-email: grisha100@gmail.com
Project-URL: Bug Tracker, https://github.com/altvod/aio-omdb/issues
Keywords: omdb
Classifier: Development Status :: 3 - Alpha
Classifier: Intended Audience :: Developers
Classifier: Topic :: Database
Classifier: Topic :: Software Development :: Libraries :: Python Modules
Classifier: Programming Language :: Python :: 3
Classifier: Programming Language :: Python :: 3 :: Only
Classifier: Programming Language :: Python :: 3.9
Classifier: Programming Language :: Python :: 3.10
Classifier: License :: OSI Approved :: MIT License
Classifier: Operating System :: OS Independent
Requires-Python: >=3.9
License-File: LICENSE
Requires-Dist: aiohttp
Requires-Dist: attrs
Requires-Dist: requests
Requires-Dist: yarl
Provides-Extra: build
Requires-Dist: build ; extra == 'build'
Requires-Dist: twine ; extra == 'build'
Provides-Extra: testing
Requires-Dist: mypy ; extra == 'testing'
Requires-Dist: pytest ; extra == 'testing'
Requires-Dist: pytest-asyncio ; extra == 'testing'
Requires-Dist: pytest-envfiles ; extra == 'testing'
Requires-Dist: types-requests ; extra == 'testing'
